content_converter/__init__.py
content_converter/cli.py
content_converter/converter.py
content_converter/factory.py
content_converter/core/__init__.py
content_converter/core/parser.py
content_converter/llm/__init__.py
content_converter/llm/base.py
content_converter/llm/gemini.py
content_converter/llm/openrouter.py
content_converter/llm/prompts.py
content_converter-1.2.0.dist-info/licenses/LICENSE
tests/__init__.py
tests/test_cli.py
tests/test_converter.py
tests/test_gemini_provider.py
tests/test_llm_provider.py
tests/test_openrouter_provider.py
tests/test_parser.py
tests/test_prompts.py
tests/e2e/__init__.py
tests/e2e/conftest.py
tests/e2e/test_basic_flow.py
content_converter-1.2.0.dist-info/METADATA
content_converter-1.2.0.dist-info/WHEEL
content_converter-1.2.0.dist-info/top_level.txt
content_converter-1.2.0.dist-info/RECORD
