Metadata-Version: 2.4
Name: content-converter
Version: 1.2.0
Summary: マークダウンファイルを各種公開プラットフォーム用に変換するツール
Home-page: https://github.com/centervil/Content-Converter
Author: Centervil
Author-email: Centervil <info@centervil.example.com>
License: MIT License
Project-URL: Homepage, https://github.com/centervil/Content-Converter
Project-URL: Repository, https://github.com/centervil/Content-Converter
Requires-Python: >=3.8
License-File: LICENSE
Requires-Dist: pyyaml>=6.0
Requires-Dist: python-frontmatter>=1.0.0
Requires-Dist: requests>=2.28.0
Requires-Dist: python-dotenv>=1.0.0
Requires-Dist: markdown>=3.4.0
Requires-Dist: pydantic>=2.5.2
Provides-Extra: oasis
Requires-Dist: oasis-article>=0.8.0; extra == "oasis"
Provides-Extra: dev
Requires-Dist: pytest>=7.3.1; extra == "dev"
Requires-Dist: pytest-cov>=4.1.0; extra == "dev"
Requires-Dist: flake8>=6.0.0; extra == "dev"
Requires-Dist: black>=23.3.0; extra == "dev"
Requires-Dist: isort>=5.12.0; extra == "dev"
Requires-Dist: mypy>=1.3.0; extra == "dev"
Dynamic: author
Dynamic: home-page
Dynamic: license-file
Dynamic: requires-python
